patchbay/__init__.py
patchbay/__main__.py
patchbay/matplotlibrc
patchbay/node.py
patchbay/patch.py
patchbay/hardware/__init__.py
patchbay/hardware/device_manager.py
patchbay/hardware/device_utils.py
patchbay/hardware/dwf_manager.py
patchbay/hardware/pyvisa_manager.py
patchbay/hardware/scpi.py
patchbay/hardware/subsystem.py
patchbay/hardware/subsystem_definitions.json
patchbay/hardware/agilent/Agilent33000.py
patchbay/hardware/agilent/AgilentN3300.py
patchbay/hardware/agilent/__init__.py
patchbay/hardware/hp/HP33120A.py
patchbay/hardware/hp/__init__.py
patchbay/hardware/magnapower/MagnaPowerSL.py
patchbay/hardware/magnapower/__init__.py
patchbay/hardware/tektronix/TektronixMSO.py
patchbay/hardware/tektronix/__init__.py
patchbay/qt/__init__.py
patchbay/qt/actions.py
patchbay/qt/patchbay_ui.py
patchbay/qt/pint_widgets.py
patchbay/resources/pb.svg
patchbay-0.0.6.dist-info/METADATA
patchbay-0.0.6.dist-info/WHEEL
patchbay-0.0.6.dist-info/entry_points.txt
patchbay-0.0.6.dist-info/licenses/LICENSE
patchbay-0.0.6.dist-info/RECORD
